{
  "family_key": "nr13_inspecao_vaso_pressao",
  "nome_exibicao": "NR13 · Inspecao de Vaso de Pressao",
  "macro_categoria": "NR13",
  "kind": "inspection",
  "wave": 1,
  "template_codes": [
    "nr13_vaso_pressao",
    "nr13_inspecao_vaso_pressao"
  ],
  "required_slots_snapshot": [
    {
      "item_id": "slot_placa_identificacao",
      "label": "Placa de identificacao",
      "required": true,
      "min_items": 1,
      "accepted_examples": [
        "foto",
        "documento"
      ],
      "purpose": "Vincular evidencia da identificacao do equipamento por placa ou documento equivalente disponivel.",
      "binding_path": "identificacao.placa_identificacao",
      "drop_folder": "coleta_entrada/slots_reais/placa_identificacao"
    },
    {
      "item_id": "slot_vista_geral_equipamento",
      "label": "Vista geral do equipamento",
      "required": true,
      "min_items": 1,
      "accepted_examples": [
        "foto"
      ],
      "purpose": "Registrar a vista geral do vaso de pressao.",
      "binding_path": "caracterizacao_do_equipamento.vista_geral_equipamento",
      "drop_folder": "coleta_entrada/slots_reais/vista_geral_equipamento"
    },
    {
      "item_id": "slot_dispositivo_seguranca",
      "label": "Dispositivo de seguranca",
      "required": true,
      "min_items": 1,
      "accepted_examples": [
        "foto"
      ],
      "purpose": "Registrar visualmente pelo menos um dispositivo de seguranca associado.",
      "binding_path": "dispositivos_e_acessorios.dispositivos_de_seguranca",
      "drop_folder": "coleta_entrada/slots_reais/dispositivo_seguranca"
    },
    {
      "item_id": "slot_condicao_geral",
      "label": "Condicao geral",
      "required": true,
      "min_items": 1,
      "accepted_examples": [
        "texto",
        "foto"
      ],
      "purpose": "Registrar a leitura da condicao geral por texto e/ou evidencia visual.",
      "binding_path": "inspecao_visual.condicao_geral",
      "drop_folder": "coleta_entrada/slots_reais/condicao_geral"
    },
    {
      "item_id": "slot_conclusao_inspecao",
      "label": "Conclusao da inspecao",
      "required": true,
      "min_items": 1,
      "accepted_examples": [
        "texto"
      ],
      "purpose": "Registrar a conclusao tecnica estruturada para revisao.",
      "binding_path": "conclusao.conclusao_tecnica",
      "drop_folder": "coleta_entrada/slots_reais/conclusao_inspecao"
    }
  ],
  "output_sections_snapshot": [
    "Identificacao",
    "Caracterizacao do equipamento",
    "Inspecao visual",
    "Dispositivos e acessorios",
    "Documentacao e registros",
    "Nao conformidades",
    "Recomendacoes",
    "Conclusao"
  ],
  "review_blocking_snapshot": [
    "escopo_principal_diferente_de_vaso_de_pressao",
    "troca_silenciosa_da_familia_principal",
    "ausencia_de_identificacao_do_vaso",
    "ausencia_de_localizacao",
    "ausencia_de_slot_obrigatorio",
    "quantidade_total_de_fotos_abaixo_do_minimo",
    "quantidade_total_de_textos_abaixo_do_minimo",
    "ausencia_de_registro_da_condicao_geral"
  ],
  "material_real_checklist": [
    {
      "item_id": "modelo_atual_vazio",
      "label": "Modelo atual vazio usado pela empresa",
      "required": true,
      "min_items": 1,
      "accepted_examples": [
        ".docx",
        ".pdf"
      ],
      "purpose": "Comparar a estrutura atual com o template_master canonico.",
      "drop_folder": "coleta_entrada/modelo_atual_vazio"
    },
    {
      "item_id": "documentos_finais_reais",
      "label": "Documentos finais reais ja emitidos",
      "required": true,
      "min_items": 3,
      "accepted_examples": [
        ".pdf",
        ".docx"
      ],
      "purpose": "Extrair linguagem, estrutura efetiva e variacoes recorrentes do documento real.",
      "drop_folder": "coleta_entrada/documentos_finais_reais"
    },
    {
      "item_id": "padrao_linguagem_tecnica",
      "label": "Padrao de linguagem tecnica e conclusao",
      "required": true,
      "min_items": 1,
      "accepted_examples": [
        ".md",
        ".txt",
        ".pdf",
        ".docx"
      ],
      "purpose": "Fixar tom, parecer, ressalvas, clausulas e assinatura que a empresa realmente usa.",
      "drop_folder": "coleta_entrada/padrao_linguagem_tecnica"
    },
    {
      "item_id": "regras_comerciais_e_operacionais",
      "label": "Regras comerciais e operacionais do servico",
      "required": true,
      "min_items": 1,
      "accepted_examples": [
        ".md",
        ".txt",
        ".pdf",
        ".docx",
        ".xlsx"
      ],
      "purpose": "Capturar o que varia por cliente, ativo, escopo e contratacao.",
      "drop_folder": "coleta_entrada/regras_comerciais_e_operacionais"
    },
    {
      "item_id": "evidencias_reais_associadas",
      "label": "Evidencias reais associadas aos documentos finais",
      "required": true,
      "min_items": 1,
      "accepted_examples": [
        ".jpg",
        ".jpeg",
        ".png",
        ".pdf",
        ".zip"
      ],
      "purpose": "Validar slots de imagem, anexos e criterios reais de evidencia.",
      "drop_folder": "coleta_entrada/evidencias_reais_associadas"
    }
  ],
  "open_questions": [
    "Qual documento atual a empresa considera referencia principal para esta familia?",
    "Quais anexos ou evidencias sao obrigatorios na pratica, mesmo quando nao estao escritos no modelo vazio?",
    "Quais campos sempre aparecem no documento final, mesmo quando o inspetor nao preencheu explicitamente em campo?",
    "Quais trechos de linguagem precisam seguir o padrao exato do engenheiro responsavel?",
    "Quais evidencias fotograficas entram no PDF final e quais ficam apenas em anexo ou acervo?",
    "Quais nao conformidades ou ressalvas sao mais recorrentes nessa familia?"
  ],
  "ingest_layout": {
    "raw_input_dir": "coleta_entrada",
    "reference_package_dir": "pacote_referencia",
    "status_file": "status_refino.json",
    "briefing_file": "briefing_real.md"
  },
  "ready_for_refinement_when": [
    "Existe ao menos 1 modelo atual vazio da empresa para a familia.",
    "Existem ao menos 3 documentos finais reais ou equivalentes para comparacao.",
    "Existe definicao de linguagem tecnica e conclusao que a empresa quer preservar.",
    "Cada slot obrigatorio do family_schema tem exemplo real ou lacuna explicitamente anotada.",
    "O material bruto ja foi separado do futuro pacote de filled_reference."
  ]
}
